mistral_lint/__init__.py
mistral_lint/__main__.py
mistral_lint/linters.py
mistral_lint/suite.py
mistral_lint/tests/conftest.py
mistral_lint/tests/test_linters.py
mistral_lint-0.2.2.dist-info/DESCRIPTION.rst
mistral_lint-0.2.2.dist-info/METADATA
mistral_lint-0.2.2.dist-info/RECORD
mistral_lint-0.2.2.dist-info/WHEEL
mistral_lint-0.2.2.dist-info/entry_points.txt
mistral_lint-0.2.2.dist-info/metadata.json
mistral_lint-0.2.2.dist-info/pbr.json
mistral_lint-0.2.2.dist-info/top_level.txt
