Metadata-Version: 2.0
Name: mistral-lint
Version: 0.2.2
Summary: Linter for Mistral Workflows
Home-page: https://github.com/d0ugal/mistral-lint
Author: Dougal Matthews
Author-email: dougal@redhat.com
License: Apache License, Version 2.0
Platform: UNKNOWN
Classifier: Environment :: Console
Classifier: Intended Audience :: Developers
Classifier: Intended Audience :: System Administrators
Classifier: License :: OSI Approved :: Apache Software License
Classifier: Natural Language :: English
Classifier: Operating System :: MacOS :: MacOS X
Classifier: Operating System :: POSIX :: Linux
Classifier: Programming Language :: Python
Classifier: Programming Language :: Python :: 2
Classifier: Programming Language :: Python :: 2.7
Classifier: Programming Language :: Python :: 3
Classifier: Programming Language :: Python :: 3.3
Classifier: Programming Language :: Python :: 3.4
Classifier: Programming Language :: Python :: 3.5
Classifier: Programming Language :: Python :: 3.6
Classifier: Topic :: Software Development
Classifier: Topic :: Utilities
Requires-Dist: Jinja2 (!=2.9.1,!=2.9.4,!=2.9.3,>=2.8,!=2.9.2,!=2.9.0)
Requires-Dist: PyYAML (>=3.10.0)
Requires-Dist: pbr (>=2.0.0)
Requires-Dist: requests (!=2.12.2,!=2.13.0,>=2.10.0)
Requires-Dist: six (>=1.9.0)
Requires-Dist: yaql (>=1.1.0)
